dlinkscraper/__init__.py
dlinkscraper/__main__.py
dlinkscraper/_duckdns_update_script.py
dlinkscraper/stolen_javascript.js
dlink_scraper-1.0.3.dist-info/LICENSE
dlink_scraper-1.0.3.dist-info/METADATA
dlink_scraper-1.0.3.dist-info/WHEEL
dlink_scraper-1.0.3.dist-info/entry_points.txt
dlink_scraper-1.0.3.dist-info/top_level.txt
dlink_scraper-1.0.3.dist-info/RECORD
