Metadata-Version: 2.1
Name: dlink-scraper
Version: 1.0.3
Summary: Scraper for getting data from D-Link DWR-921 LTE router
Home-page: https://github.com/TheLastGimbus/D-Link_Scraper
Author: TheLastGimbus
Author-email: mateusz.soszynski@tuta.io
License: Apache
Platform: UNKNOWN
Classifier: Programming Language :: Python :: 3
Classifier: License :: OSI Approved :: Apache Software License
Classifier: Development Status :: 5 - Production/Stable
Classifier: Intended Audience :: Developers
Classifier: Intended Audience :: System Administrators
Classifier: Intended Audience :: Telecommunications Industry
Classifier: Topic :: Internet :: WWW/HTTP
Classifier: Topic :: System :: Networking :: Monitoring
Requires-Dist: beautifulsoup4
Requires-Dist: py-mini-racer
Requires-Dist: pycryptodome
Requires-Dist: requests
